{
  "project_info": {
    "project_number": "1062680284266",
    "project_id": "mehendi-studio",
    "storage_bucket": "mehendi-studio.appspot.com"
  },
  "client": [
    {
      "client_info": {
        "mobilesdk_app_id": "1:1062680284266:android:7a12daf15208eee6768e13",
        "android_client_info": {
          "package_name": "com.studio.restncode.mehndidesigns"
        }
      },
      "oauth_client": [
        {
          "client_id": "1062680284266-hb9k15mauncmtvp17nop7mmvb5lt24jv.apps.googleusercontent.com",
          "client_type": 3
        }
      ],
      "api_key": [
        {
          "current_key": "AIzaSyCuOwYOd9TPcxeh3Wv-EwZ2Nv0Nv7mAP40"
        }
      ],
      "services": {
        "appinvite_service": {
          "other_platform_oauth_client": [
            {
              "client_id": "1062680284266-hb9k15mauncmtvp17nop7mmvb5lt24jv.apps.googleusercontent.com",
              "client_type": 3
            }
          ]
        }
      }
    }
  ],
  "configuration_version": "1"
}